LICENSE.txt
MANIFEST.in
README.rst
setup.py
gpsdio_density/__init__.py
gpsdio_density/core.py
gpsdio_density.egg-info/PKG-INFO
gpsdio_density.egg-info/SOURCES.txt
gpsdio_density.egg-info/dependency_links.txt
gpsdio_density.egg-info/entry_points.txt
gpsdio_density.egg-info/requires.txt
gpsdio_density.egg-info/top_level.txt
gpsdio_density.egg-info/zip-safe
tests/test_core.py