Metadata-Version: 1.1
Name: gpsdio-density
Version: 0.2
Summary: A plugin for gpsdio for computing AIS density rasters.
Home-page: https://github.com/SkyTruth/gpsdio-density
Author: Kevin Wurster
Author-email: kevin@skytruth.org
License: Copyright 2014-2015 SkyTruth
